[
  {
    "id": "3",
    "name": "Summer Smith",
    "image": "https://rickandmortyapi.com/api/character/avatar/3.jpeg",
    "species": "Human"
  },
  {
    "id": "4",
    "name": "Beth Smith",
    "image": "https://rickandmortyapi.com/api/character/avatar/4.jpeg",
    "species": "Human"
  },
  {
    "id": "6",
    "name": "Abadango Cluster Princess",
    "image": "https://rickandmortyapi.com/api/character/avatar/6.jpeg",
    "species": "Alien"
  },
  {
    "id": "134",
    "name": "Garmanarnar",
    "image": "https://rickandmortyapi.com/api/character/avatar/134.jpeg",
    "species": "Alien"
  }
]